citableclass/__init__.py
citableclass/base.py
citableclass/utils.py
citableclass-0.0.21.dist-info/DESCRIPTION.rst
citableclass-0.0.21.dist-info/METADATA
citableclass-0.0.21.dist-info/RECORD
citableclass-0.0.21.dist-info/WHEEL
citableclass-0.0.21.dist-info/metadata.json
citableclass-0.0.21.dist-info/top_level.txt
