Metadata-Version: 2.0
Name: citableclass
Version: 0.0.21
Summary: Tool for data request to Edition Topoi
Home-page: http://pypi.python.org/pypi/citableclass/
Author: Gordon Fischer, Malte Vogl
Author-email: gordon.fischer@topoi.org
License: LICENSE.txt
Download-URL: https://github.com/TOPOI-DH/citableclass/archive/0.0.21.tar.gz
Project-URL: Source, https://github.com/TOPOI-DH/citableclass/
Project-URL: Tracker, https://github.com/TOPOI-DH/citableclass/issues
Platform: UNKNOWN
Classifier: Development Status :: 3 - Alpha
Classifier: Intended Audience :: Science/Research
Classifier: Topic :: Text Processing :: General
Classifier: Topic :: Text Processing :: Indexing
Classifier: License :: OSI Approved :: GNU General Public License v3 (GPLv3)
Classifier: Programming Language :: Python :: 3
Requires-Python: >=3
Requires-Dist: pandas
Requires-Dist: numpy
Requires-Dist: matplotlib
Requires-Dist: requests
Requires-Dist: IPython
Requires-Dist: pyyaml
